{
    "directed": false,
    "multigraph": false,
    "graph": {},
    "nodes": [
        {
            "type": "patient",
            "id": "Patient_0164"
        },
        {
            "type": "abnormality",
            "id": "opacities"
        },
        {
            "type": "abnormality",
            "id": "atelectasis"
        },
        {
            "type": "abnormality",
            "id": "subsegmental atelectasis"
        }
    ],
    "links": [
        {
            "relationship": "HAS_ABNORMALITY",
            "source": "Patient_0164",
            "target": "opacities"
        },
        {
            "relationship": "HAS_ABNORMALITY",
            "source": "Patient_0164",
            "target": "atelectasis"
        },
        {
            "relationship": "HAS_ABNORMALITY",
            "source": "Patient_0164",
            "target": "subsegmental atelectasis"
        }
    ]
}